haravan/__init__.py
haravan/base.py
haravan/mixins.py
haravan/session.py
haravan/version.py
haravan/yamlobjects.py
haravan/resources/__init__.py
haravan/resources/address.py
haravan/resources/application_charge.py
haravan/resources/article.py
haravan/resources/asset.py
haravan/resources/billing_address.py
haravan/resources/blog.py
haravan/resources/carrier_service.py
haravan/resources/cart.py
haravan/resources/checkout.py
haravan/resources/collect.py
haravan/resources/comment.py
haravan/resources/country.py
haravan/resources/custom_collection.py
haravan/resources/customer.py
haravan/resources/customer_group.py
haravan/resources/customer_saved_search.py
haravan/resources/event.py
haravan/resources/fulfillment.py
haravan/resources/fulfillment_service.py
haravan/resources/image.py
haravan/resources/line_item.py
haravan/resources/metafield.py
haravan/resources/note_attribute.py
haravan/resources/option.py
haravan/resources/order.py
haravan/resources/order_risk.py
haravan/resources/page.py
haravan/resources/payment_details.py
haravan/resources/policy.py
haravan/resources/product.py
haravan/resources/product_search_engine.py
haravan/resources/province.py
haravan/resources/receipt.py
haravan/resources/recurring_application_charge.py
haravan/resources/redirect.py
haravan/resources/rule.py
haravan/resources/script_tag.py
haravan/resources/shipping_address.py
haravan/resources/shipping_line.py
haravan/resources/shop.py
haravan/resources/smart_collection.py
haravan/resources/tax_line.py
haravan/resources/theme.py
haravan/resources/transaction.py
haravan/resources/variant.py
haravan/resources/webhook.py
haravan-2.1.1.data/scripts/haravan_api.py
haravan-2.1.1.dist-info/LICENSE
haravan-2.1.1.dist-info/METADATA
haravan-2.1.1.dist-info/WHEEL
haravan-2.1.1.dist-info/top_level.txt
haravan-2.1.1.dist-info/RECORD
